dm_client/__init__.py
dm_client/app/__init__.py
dm_client/app/cas/__init__.py
dm_client/app/cas/apps.py
dm_client/app/cas/crypto.py
dm_client/app/cas/errors.py
dm_client/app/cas/models.py
dm_client/app/cas/serializers.py
dm_client/app/cas/session.py
dm_client/app/cas/urls.py
dm_client/app/cas/views.py
dm_client/app/cas/migrations/0001_initial.py
dm_client/app/cas/migrations/__init__.py
dm_client/app/cas/migrations_cd/__init__.py
dm_client/app/cas/migrations_cd/migration_001_20221106_0824_usersessionlog_create.py
dm_client/app/cas/tests/__init__.py
dm_client_app_cas-1.0.1.dist-info/licenses/LICENSE
dm_client_app_cas-1.0.1.dist-info/METADATA
dm_client_app_cas-1.0.1.dist-info/WHEEL
dm_client_app_cas-1.0.1.dist-info/top_level.txt
dm_client_app_cas-1.0.1.dist-info/RECORD
